configlayer/__init__.py
configlayer/_config.py
configlayer/_file.py
configlayer/_io.py
configlayer/_profiles.py
configlayer/constants.py
configlayer/exceptions.py
configlayer/types.py
configlayer/utils.py
configlayer-0.1.2.dist-info/LICENSE
configlayer-0.1.2.dist-info/METADATA
configlayer-0.1.2.dist-info/WHEEL
configlayer-0.1.2.dist-info/top_level.txt
configlayer-0.1.2.dist-info/RECORD
