Metadata-Version: 2.1
Name: configlayer
Version: 0.1.2
Summary: Package for simplified work with configurations (as dataclass), manage their profiles, and export/import possibilities
Author-email: Timoshenko Maxim <cooold.tm@gmail.com>
Project-URL: Homepage, https://github.com/c0oo1d/configlayer
Project-URL: Bug Tracker, https://github.com/c0oo1d/configlayer/issues
Classifier: Programming Language :: Python
Classifier: Programming Language :: Python :: 3
Classifier: Programming Language :: Python :: 3 :: Only
Classifier: Programming Language :: Python :: 3.10
Classifier: Programming Language :: Python :: 3.11
Classifier: License :: OSI Approved :: MIT License
Classifier: Operating System :: OS Independent
Requires-Python: >=3.10
License-File: LICENSE
